{
  "app-welcome": "Привет!",
  "app-open-project": "Открыть",
  "app-save-project": "Сохранить",
  "app-save-as-project": "Сохранить как",
  "app-new-project": "Создать",
  "app-close-application": "Закрыть программу",
  "app-recent": "проекты",
  "app-recent-header": "Ранее открытые",
  "app-main-tab-name": "Главная",
  "tree-plugin-tooltip": "Плагин",
  "tree-group-tooltip": "Группа",
  "tree-install-step-tooltip": "Установочный шаг",
  "tree-project-root-tooltip": "Корень проекта",
  "dependencyPattern-button-change-type": "Сменить тип",
  "conditionalFileInstall-button-refresh": "Обновить номера",
  "dependencyPattern-button-refresh": "Обновить номера",
  "group-info": "Информация о группе",
  "group-name": "Имя группы",
  "group-type": "Тип группы",
  "group-other-settings": "Иные настройки",
  "group-plugins-order": "Сортировка плагинов",
  "installStep-info": "Информация",
  "installStep-step-name": "Тия шага",
  "installStep-other-settings": "Иные настройки",
  "installStep-groups-order": "Сортировка групп",
  "compositeDependency-title": "Комплексные зависимости",
  "compositeDependency-operator": "Оператор композиции",
  "compositeDependency-files-dependency": "Файловые зависимости",
  "compositeDependency-file-status": "Статус",
  "compositeDependency-file-name": "Имя",
  "compositeDependency-flag-dependency": "Флаговая зависимость",
  "compositeDependency-flag-value": "Значение",
  "compositeDependency-flag-name": "Имя",
  "plugin-info": "Плагин",
  "plugin-name": "Имя",
  "plugin-description": "Описание",
  "plugin-image": "Банер",
  "plugin-files-and-folders": "Файлы и папки",
  "plugin-condition-flags": "Флаги состояния",
  "image-path": "Путь",
  "image-show": "Показать",
  "image-height": "Высота",
  "image-show-fade": "Показать затенение",
  "fileList-destination-button-ok": "OK",
  "fileList-source": "Файл",
  "fileList-destination": "Назначение",
  "fileList-always-install": "Всегда устанавливать",
  "fileList-install-if-usable": "Установить если возможно",
  "fileList-priority": "Приоритет",
  "conditionFlag-value": "Значение",
  "conditionFlag-name": "Имя",
  "pluginTypeDescriptor-title": "Тип плагина",
  "pluginTypeDescriptor-plugin-type": "Тип",
  "pluginTypeDescriptor-dependency-type": "Тип зависимости",
  "pluginTypeDescriptor-default-plugin-type": "Тип по умолчанию",
  "dependencyPattern-plugin-type": "Тип плагина*",
  "dependencyPattern-pattern": "Шаблон",
  "dependencyPattern-dependency-type": "Тип зависимости",
  "project-mod-info-settings": "Настройки мода",
  "project-module-name": "Имя модуля",
  "project-author": "Автор",
  "project-version": "Версия",
  "project-website": "Сайт",
  "project-category": "Категория",
  "project-description": "Описание",
  "project-module-title": "Настройки заголовка",
  "project-module-title-field": "Заголовок",
  "project-color": "Цвет",
  "project-position": "Позиция",
  "project-other-settings-title": "Иные настройки",
  "project-install-step-order": "Сортировка шагов установки",
  "project-image": "Банер",
  "project-files-and-folder-title": "Файлы и папки",
  "conditionalFileInstall-title": "Условные флаги",
  "conditionalFileInstall-pattern": "Шаблон",
  "conditionalFileInstall-file-list-title": "Список файлов",
  "group-info-tooltip": "Без описания",
  "group-name-tooltip": "Без описания",
  "group-type-tooltip": "Без описания",
  "group-other-settings-tooltip": "Без описания",
  "group-plugins-order-tooltip": "Без описания",
  "installStep-info-tooltip": "Без описания",
  "installStep-step-name-tooltip": "Без описания",
  "installStep-other-settings-tooltip": "Без описания",
  "installStep-groups-order-tooltip": "Без описания",
  "compositeDependency-title-tooltip": "Без описания",
  "compositeDependency-operator-tooltip": "Без описания",
  "compositeDependency-files-dependency-tooltip": "Без описания",
  "compositeDependency-file-status-tooltip": "Без описания",
  "compositeDependency-file-name-tooltip": "Без описания",
  "compositeDependency-flag-dependency-tooltip": "Без описания",
  "compositeDependency-flag-value-tooltip": "Без описания",
  "compositeDependency-flag-name-tooltip": "Без описания",
  "plugin-info-tooltip": "Без описания",
  "plugin-name-tooltip": "Без описания",
  "plugin-description-tooltip": "Без описания",
  "plugin-image-tooltip": "Без описания",
  "image-path-tooltip": "Без описания",
  "image-show-tooltip": "Без описания",
  "image-height-tooltip": "Без описания",
  "fileList-destination-button-ok-tooltip": "Без описания",
  "fileList-source-tooltip": "Без описания",
  "fileList-destination-tooltip": "Без описания",
  "fileList-always-install-tooltip": "Без описания",
  "fileList-install-if-usable-tooltip": "Без описания",
  "fileList-priority-tooltip": "Без описания",
  "conditionFlag-value-tooltip": "Без описания",
  "conditionFlag-name-tooltip": "Без описания",
  "pluginTypeDescriptor-title-tooltip": "Без описания",
  "pluginTypeDescriptor-plugin-type-tooltip": "Без описания",
  "pluginTypeDescriptor-dependency-type-tooltip": "Без описания",
  "pluginTypeDescriptor-default-plugin-type-tooltip": "Без описания",
  "dependencyPattern-plugin-type-tooltip": "Без описания",
  "dependencyPattern-pattern-tooltip": "Без описания",
  "dependencyPattern-dependency-type-tooltip": "Без описания",
  "project-mod-info-settings-tooltip": "Без описания",
  "project-module-name-tooltip": "Без описания",
  "project-author-tooltip": "Без описания",
  "project-version-tooltip": "Без описания",
  "project-website-tooltip": "Без описания",
  "project-category-tooltip": "Без описания",
  "project-description-tooltip": "Без описания",
  "project-module-title-tooltip": "Без описания",
  "project-module-title-field-tooltip": "Без описания",
  "project-color-tooltip": "Без описания",
  "project-position-tooltip": "Без описания",
  "project-other-settings-title-tooltip": "Без описания",
  "project-install-step-order-tooltip": "Без описания",
  "project-image-tooltip": "Без описания",
  "project-files-and-folder-title-tooltip": "Без описания",
  "conditionalFileInstall-title-tooltip": "Без описания",
  "conditionalFileInstall-pattern-tooltip": "Без описания",
  "conditionalFileInstall-file-list-title-tooltip": "Без описания",
  "ModuleTitlePosition-Left": "Лево",
  "ModuleTitlePosition-Right": "Право",
  "ModuleTitlePosition-RightOfImage": "Справа от банера",
  "Boolean-True": "Да",
  "Boolean-False": "Нет",
  "OrderEnum-Ascending": "По возрастанию",
  "OrderEnum-Descending": "По убыванию",
  "OrderEnum-Explicit": "По порядку",
  "CompositeDependencyOperator-And": "И",
  "CompositeDependencyOperator-Or": "ИЛИ",
  "FileDependencyState-Missing": "Отсутствует",
  "FileDependencyState-Inactive": "Не активный",
  "FileDependencyState-Active": "Активный",
  "GroupType-SelectAtLeastOne": "Выбрать по крайней мере один",
  "GroupType-SelectAtMostOne": "Выбрать максимум",
  "GroupType-SelectExactlyOne": "Выбрать Точно один",
  "GroupType-SelectAll": "Выбрать все",
  "GroupType-SelectAny": "Выбрать любой",
  "ItemsChoiceType-Dependencies": "Зависимости",
  "ItemsChoiceType-FileDependency": "Файл зависимость",
  "ItemsChoiceType-FlagDependency": "Флаг зависимость",
  "ItemsChoiceType-FommDependency": "Фом зависимость",
  "ItemsChoiceType-GameDependency": "Игровая зависимость",
  "ItemsChoiceType1-File": "Файл",
  "ItemsChoiceType1-Folder": "Папка",
  "PluginTypeEnum-Required": "Обязательно",
  "PluginTypeEnum-Optional": "Не обязательно",
  "PluginTypeEnum-Recommended": "Рекомендовано",
  "PluginTypeEnum-NotUsable": "Не используется",
  "PluginTypeEnum-CouldBeUsable": "Полезно",
  "CategoriesEnum-Category1": "Default",
  "CategoriesEnum-Category2": "Miscellaneous",
  "CategoriesEnum-Category3": "Ammo",
  "CategoriesEnum-Category4": "Animation",
  "CategoriesEnum-Category5": "Armour",
  "CategoriesEnum-Category6": "BugFixes",
  "CategoriesEnum-Category7": "Buildings",
  "CategoriesEnum-Category8": "CheatsandGoditems",
  "CategoriesEnum-Category9": "Clothing",
  "CategoriesEnum-Category10": "Collectibles,TreasureHunts,andPuzzles",
  "CategoriesEnum-Category11": "Companions",
  "CategoriesEnum-Category12": "Creatures",
  "CategoriesEnum-Category13": "ENBPresets",
  "CategoriesEnum-Category14": "Environment",
  "CategoriesEnum-Category15": "GameplayEffectsandChanges",
  "CategoriesEnum-Category16": "Factions",
  "CategoriesEnum-Category17": "HairandFaceModels",
  "CategoriesEnum-Category18": "ModdersResourcesandTutorials",
  "CategoriesEnum-Category19": "ModelsandTextures",
  "CategoriesEnum-Category20": "NewLands",
  "CategoriesEnum-Category21": "Locations-New",
  "CategoriesEnum-Category22": "NPC",
  "CategoriesEnum-Category23": "NPC-Vendors",
  "CategoriesEnum-Category24": "Overhauls",
  "CategoriesEnum-Category25": "Patches",
  "CategoriesEnum-Category26": "Performances",
  "CategoriesEnum-Category27": "Perks",
  "CategoriesEnum-Category28": "PlayerHomes",
  "CategoriesEnum-Category29": "Poses",
  "CategoriesEnum-Category30": "QuestsandAdventures",
  "CategoriesEnum-Category31": "Radio",
  "CategoriesEnum-Category32": "SavedGames/Characters",
  "CategoriesEnum-Category33": "Audio-SFX",
  "CategoriesEnum-Category34": "Audio-Music",
  "CategoriesEnum-Category35": "Audio-Misc",
  "CategoriesEnum-Category36": "Audio-Voice",
  "CategoriesEnum-Category37": "UserInterface",
  "CategoriesEnum-Category38": "Utilities",
  "CategoriesEnum-Category39": "Vehicles",
  "CategoriesEnum-Category40": "VisualsandGraphics",
  "CategoriesEnum-Category41": "Weapons",
  "CategoriesEnum-Category42": "WeaponsandArmour",
  "CategoriesEnum-Category43": "Items-Food/Drinks/Chems/etc",
  "CategoriesEnum-Category44": "Crafting-Equipment",
  "CategoriesEnum-Category45": "Crafting-Home",
  "CategoriesEnum-Category46": "SkillsandLeveling",
  "CategoriesEnum-Category47": "Locations-Vanilla",
  "CategoriesEnum-Category48": "PlayerSettlement",
  "CategoriesEnum-Category49": "Clothing-Backpacks",
  "CategoriesEnum-Category50": "Crafting-Other",
  "CategoriesEnum-Category51": "Immersion",
  "CategoriesEnum-Category52": "Pip-boy",
  "CategoriesEnum-Category53": "PowerArmour",
  "CategoriesEnum-Category54": "Immersion",
  "CategoriesEnum-Category55": "ReShadePresets",
  "CategoriesEnum-Category56": "Weather",
  "CategoriesEnum-Category57": "Tattoos"
}
